v1-0.12.3-py3.6-nspkg.pth
google/iam/v1/__init__.py
google/iam/v1/iam_policy_pb2.py
google/iam/v1/iam_policy_pb2_grpc.py
google/iam/v1/options_pb2.py
google/iam/v1/options_pb2_grpc.py
google/iam/v1/policy_pb2.py
google/iam/v1/policy_pb2_grpc.py
google/iam/v1/logging/__init__.py
google/iam/v1/logging/audit_data_pb2.py
v1-0.12.3.dist-info/LICENSE
v1-0.12.3.dist-info/METADATA
v1-0.12.3.dist-info/WHEEL
v1-0.12.3.dist-info/namespace_packages.txt
v1-0.12.3.dist-info/top_level.txt
v1-0.12.3.dist-info/RECORD
