Metadata-Version: 2.1
Name: v1
Version: 0.12.3
Summary: GRPC library for the google-iam-v1 service
Home-page: https://github.com/googleapis/googleapis
Author: Google Inc
Author-email: googleapis-packages@google.com
License: Apache-2.0
Platform: UNKNOWN
Classifier: Intended Audience :: Developers
Classifier: Development Status :: 3 - Alpha
Classifier: Intended Audience :: Developers
Classifier: License :: OSI Approved :: Apache Software License
Classifier: Programming Language :: Python
Classifier: Programming Language :: Python :: 2
Classifier: Programming Language :: Python :: 2.7
Classifier: Programming Language :: Python :: 3
Classifier: Programming Language :: Python :: 3.4
Classifier: Programming Language :: Python :: 3.5
Classifier: Programming Language :: Python :: Implementation :: CPython
Requires-Dist: grpcio (<2.0.0dev,>=1.0.0)
Requires-Dist: googleapis-common-protos[grpc] (<2.0.0dev,>=1.5.2)
